{
    "colorful": {},
    "filled": {
        "account-book-filled": {
            "key": "account-book-filled",
            "theme": "filled",
            "name": "",
            "version": "",
            "status": "stage",
            "design": "xxx"
        },
        "account-book-filled-copy": {
            "key": "account-book-filled-copy",
            "theme": "filled",
            "name": "",
            "version": "",
            "status": "error",
            "design": "xxx"
        }
    }
}
